safe_ruamel.py
safe_ruamel-0.2.0.dist-info/LICENSE
safe_ruamel-0.2.0.dist-info/WHEEL
safe_ruamel-0.2.0.dist-info/METADATA
safe_ruamel-0.2.0.dist-info/RECORD
